<?xml version="1.0" encoding="UTF-8"?><record_update table="sp_container">
    <sp_container action="INSERT_OR_UPDATE">
        <background_color/>
        <background_image/>
        <background_style>default</background_style>
        <bootstrap_alt>false</bootstrap_alt>
        <class_name/>
        <container_class_name/>
        <name>Add Systems - Container 1</name>
        <order>1</order>
        <sp_page display_value="add_systems">b5620faddb323300e16bd426ca96196a</sp_page>
        <subheader>false</subheader>
        <sys_class_name>sp_container</sys_class_name>
        <sys_created_by>timothy.baker</sys_created_by>
        <sys_created_on>2019-07-22 13:40:13</sys_created_on>
        <sys_id>31620faddb323300e16bd426ca96196d</sys_id>
        <sys_mod_count>1</sys_mod_count>
        <sys_name>Add Systems - Container 1</sys_name>
        <sys_package display_value="vasi_prototype" source="x_368247_vasi_prot">18ecdf4ddb063300e16bd426ca961977</sys_package>
        <sys_policy/>
        <sys_scope display_value="vasi_prototype">18ecdf4ddb063300e16bd426ca961977</sys_scope>
        <sys_update_name>sp_container_31620faddb323300e16bd426ca96196d</sys_update_name>
        <sys_updated_by>timothy.baker</sys_updated_by>
        <sys_updated_on>2019-07-22 13:47:21</sys_updated_on>
        <title/>
        <width>container-fluid</width>
    </sp_container>
</record_update>
